odoo/addons/ssi_l10n_id_taxform_bukti_potong_pph_mixin/README.rst
odoo/addons/ssi_l10n_id_taxform_bukti_potong_pph_mixin/__init__.py
odoo/addons/ssi_l10n_id_taxform_bukti_potong_pph_mixin/__manifest__.py
odoo/addons/ssi_l10n_id_taxform_bukti_potong_pph_mixin/menu.xml
odoo/addons/ssi_l10n_id_taxform_bukti_potong_pph_mixin/data/data_decimal_precision.xml
odoo/addons/ssi_l10n_id_taxform_bukti_potong_pph_mixin/models/__init__.py
odoo/addons/ssi_l10n_id_taxform_bukti_potong_pph_mixin/models/bukti_potong_pph_line_mixin.py
odoo/addons/ssi_l10n_id_taxform_bukti_potong_pph_mixin/models/bukti_potong_pph_mixin.py
odoo/addons/ssi_l10n_id_taxform_bukti_potong_pph_mixin/models/bukti_potong_pph_type.py
odoo/addons/ssi_l10n_id_taxform_bukti_potong_pph_mixin/security/ir.model.access.csv
odoo/addons/ssi_l10n_id_taxform_bukti_potong_pph_mixin/security/res_group_data.xml
odoo/addons/ssi_l10n_id_taxform_bukti_potong_pph_mixin/static/description/icon.png
odoo/addons/ssi_l10n_id_taxform_bukti_potong_pph_mixin/views/bukti_potong_pph_mixin_views.xml
odoo/addons/ssi_l10n_id_taxform_bukti_potong_pph_mixin/views/bukti_potong_pph_type_views.xml
odoo14_addon_ssi_l10n_id_taxform_bukti_potong_pph_mixin-14.0.1.6.0.dist-info/METADATA
odoo14_addon_ssi_l10n_id_taxform_bukti_potong_pph_mixin-14.0.1.6.0.dist-info/WHEEL
odoo14_addon_ssi_l10n_id_taxform_bukti_potong_pph_mixin-14.0.1.6.0.dist-info/top_level.txt
odoo14_addon_ssi_l10n_id_taxform_bukti_potong_pph_mixin-14.0.1.6.0.dist-info/RECORD
